ml_random_utils/__init__.py
ml_random_utils/data.py
ml_random_utils/dataframes.py
ml_random_utils/decorators.py
ml_random_utils/dicts.py
ml_random_utils/files.py
ml_random_utils/functions.py
ml_random_utils/lists.py
ml_random_utils/paths.py
ml_random_utils/seed.py
ml_random_utils/text.py
ml_random_utils-0.0.2.dist-info/LICENSE
ml_random_utils-0.0.2.dist-info/METADATA
ml_random_utils-0.0.2.dist-info/WHEEL
ml_random_utils-0.0.2.dist-info/RECORD
