Metadata-Version: 2.1
Name: ml-random-utils
Version: 0.0.2
Summary: Random utilities I use in ML projects.
License: MIT
Author: Marco Podda
Requires-Python: >=3.10,<4.0
Classifier: License :: OSI Approved :: MIT License
Classifier: Programming Language :: Python :: 3
Classifier: Programming Language :: Python :: 3.10
Classifier: Programming Language :: Python :: 3.11
Requires-Dist: numpy (>=1.24.2,<2.0.0)
Requires-Dist: pandas (>=1.5.3,<2.0.0)
Requires-Dist: scikit-learn (>=1.2.2,<2.0.0)
